geopackage/__init__.py
geopackage/_coord.py
geopackage/_geopackage.py
geopackage/_gpkg.py
geopackage/_rtree.py
geopackage/_utils.py
geopackage/_wkb.py
geopackage/prj.json
geopackage-1.0.0.dist-info/METADATA
geopackage-1.0.0.dist-info/RECORD
geopackage-1.0.0.dist-info/WHEEL
geopackage-1.0.0.dist-info/top_level.txt
