Metadata-Version: 2.1
Name: geopackage
Version: 1.0.0
Summary: Pure Python reader/writer of geopackages
Home-page: https://github.com/achapkowski/pygeopackage
Author: Andrew Chapkowski
Author-email: andrewonboe@gmail.com
License: Apache License 2.0
Requires-Dist: pandas
